{
    "word2vec_vs500_win7_sg0": {
        "catboost": {
            "f1": 0.7643736972643369,
            "auc": 0.8036510313009412,
            "f1_list": [
                0.7631763879128602,
                0.7610371408549403,
                0.7689075630252102
            ],
            "auc_list": [
                0.8027779691062864,
                0.8009581328915457,
                0.8072169919049915
            ]
        },
        "lightgbm": {
            "f1": 0.7482319660537482,
            "auc": 0.7912070250994808,
            "f1_list": [
                0.7482319660537482,
                0.7482319660537482,
                0.7482319660537482
            ],
            "auc_list": [
                0.7912070250994808,
                0.7912070250994808,
                0.7912070250994808
            ]
        },
        "knn": {
            "f1": 0.7082909798028904,
            "auc": 0.7585234836611495,
            "f1_list": [
                0.7189542483660132,
                0.6836964688204358,
                0.7222222222222222
            ],
            "auc_list": [
                0.7619301381069594,
                0.7461648703940682,
                0.7674754424824209
            ]
        },
        "randomforest": {
            "f1": 0.7227898047648118,
            "auc": 0.7738605783115641,
            "f1_list": [
                0.7276752767527674,
                0.7144948755490483,
                0.7261992619926199
            ],
            "auc_list": [
                0.77776670086412,
                0.7671673028843075,
                0.7766477311862648
            ]
        },
        "decisiontree": {
            "f1": 0.6323299373255068,
            "auc": 0.6886642088002253,
            "f1_list": [
                0.630118890356671,
                0.6323432343234323,
                0.634527687296417
            ],
            "auc_list": [
                0.6875246964824958,
                0.689307676784521,
                0.6891602531336589
            ]
        }
    },
    "word2vec_vs500_win6_sg1": {
        "catboost": {
            "f1": 0.761886534342299,
            "auc": 0.8023310659898067,
            "f1_list": [
                0.7581792318634424,
                0.7651677373304784,
                0.7623126338329764
            ],
            "auc_list": [
                0.7993225762403827,
                0.8049542805423741,
                0.8027163411866638
            ]
        },
        "lightgbm": {
            "f1": 0.74835886214442,
            "auc": 0.7928667495622604,
            "f1_list": [
                0.7483588621444202,
                0.7483588621444202,
                0.7483588621444202
            ],
            "auc_list": [
                0.7928667495622604,
                0.7928667495622604,
                0.7928667495622604
            ]
        },
        "knn": {
            "f1": 0.7076560471032977,
            "auc": 0.7626340256202971,
            "f1_list": [
                0.7184334908845376,
                0.69224620303757,
                0.7122884473877851
            ],
            "auc_list": [
                0.76408167753614,
                0.7579442617760682,
                0.7658761375486831
            ]
        },
        "randomforest": {
            "f1": 0.7104437282420649,
            "auc": 0.7684784066645157,
            "f1_list": [
                0.7135135135135134,
                0.7133956386292835,
                0.7044220325833981
            ],
            "auc_list": [
                0.7703761840717204,
                0.7709048549508366,
                0.7641541809709902
            ]
        },
        "decisiontree": {
            "f1": 0.6213908431019951,
            "auc": 0.6846265730727882,
            "f1_list": [
                0.6270491803278688,
                0.6155932203389831,
                0.6215301286391334
            ],
            "auc_list": [
                0.6901311949653615,
                0.6795317969855489,
                0.6842167272674543
            ]
        }
    },
    "word2vec_vs500_win6_sg0": {
        "catboost": {
            "f1": 0.7700500565630821,
            "auc": 0.8077827200952533,
            "f1_list": [
                0.7713690062543432,
                0.7742382271468145,
                0.7645429362880888
            ],
            "auc_list": [
                0.8089262603815857,
                0.8111273438245804,
                0.8032945560795942
            ]
        },
        "lightgbm": {
            "f1": 0.7478753541076487,
            "auc": 0.790997973528996,
            "f1_list": [
                0.7478753541076487,
                0.7478753541076487,
                0.7478753541076487
            ],
            "auc_list": [
                0.790997973528996,
                0.790997973528996,
                0.790997973528996
            ]
        },
        "knn": {
            "f1": 0.7024242629330876,
            "auc": 0.7551623452605511,
            "f1_list": [
                0.7068166776968895,
                0.6728110599078342,
                0.7276450511945393
            ],
            "auc_list": [
                0.7526708452812952,
                0.7403361984274004,
                0.7724799920729578
            ]
        },
        "randomforest": {
            "f1": 0.7313792374667157,
            "auc": 0.7805169978261053,
            "f1_list": [
                0.7292899408284024,
                0.7315634218289085,
                0.7332843497428362
            ],
            "auc_list": [
                0.7791315780251755,
                0.7806686508440004,
                0.78175076460914
            ]
        },
        "decisiontree": {
            "f1": 0.6306763867401343,
            "auc": 0.6855574366168931,
            "f1_list": [
                0.6340508806262232,
                0.6240208877284595,
                0.6339573918657199
            ],
            "auc_list": [
                0.6889512015631741,
                0.680454403194018,
                0.6872667050934871
            ]
        }
    },
    "word2vec_vs500_win7_sg1": {
        "catboost": {
            "f1": 0.7718198239449157,
            "auc": 0.8102826788085752,
            "f1_list": [
                0.7730851825340014,
                0.7794432548179872,
                0.7629310344827587
            ],
            "auc_list": [
                0.8112499954685353,
                0.8161439773209256,
                0.8034540636362648
            ]
        },
        "lightgbm": {
            "f1": 0.7571839080459771,
            "auc": 0.7989781849248442,
            "f1_list": [
                0.7571839080459771,
                0.7571839080459771,
                0.7571839080459771
            ],
            "auc_list": [
                0.7989781849248442,
                0.7989781849248442,
                0.7989781849248442
            ]
        },
        "knn": {
            "f1": 0.7018045818259244,
            "auc": 0.7582155454614661,
            "f1_list": [
                0.7150610583446404,
                0.6788844621513944,
                0.7114682249817386
            ],
            "auc_list": [
                0.7616715425226602,
                0.7482916378163414,
                0.7646834560453968
            ]
        },
        "randomforest": {
            "f1": 0.7098512647165428,
            "auc": 0.7681996712372025,
            "f1_list": [
                0.7129485179407177,
                0.7087227414330218,
                0.7078825347758887
            ],
            "auc_list": [
                0.7706958033803517,
                0.7675479459172712,
                0.7663552644139848
            ]
        },
        "decisiontree": {
            "f1": 0.609682906404744,
            "auc": 0.6710925985674127,
            "f1_list": [
                0.6085219707057256,
                0.6016042780748664,
                0.61892247043364
            ],
            "auc_list": [
                0.6706048115696148,
                0.6655017781467396,
                0.6771712059858835
            ]
        }
    },
    "word2vec_vs500_win3_sg0": {
        "catboost": {
            "f1": 0.7638402993748682,
            "auc": 0.8028887382428631,
            "f1_list": [
                0.7611731843575419,
                0.7644197359277276,
                0.7659279778393352
            ],
            "auc_list": [
                0.8009212769788302,
                0.8033314119923098,
                0.8044135257574494
            ]
        },
        "lightgbm": {
            "f1": 0.7443502824858758,
            "auc": 0.7880591676364,
            "f1_list": [
                0.7443502824858758,
                0.7443502824858758,
                0.7443502824858758
            ],
            "auc_list": [
                0.7880591676364002,
                0.7880591676364002,
                0.7880591676364002
            ]
        },
        "knn": {
            "f1": 0.7045385036837272,
            "auc": 0.757461711137454,
            "f1_list": [
                0.7188328912466843,
                0.6717909300538047,
                0.7229916897506925
            ],
            "auc_list": [
                0.7629874798651919,
                0.7396721878032304,
                0.7697254657439396
            ]
        },
        "randomforest": {
            "f1": 0.7299765176479257,
            "auc": 0.7793037736829449,
            "f1_list": [
                0.7372316802368616,
                0.7308823529411765,
                0.7218155197657394
            ],
            "auc_list": [
                0.7851813854681365,
                0.7799677843071149,
                0.7727621512735832
            ]
        },
        "decisiontree": {
            "f1": 0.6289202707003457,
            "auc": 0.6859958809993069,
            "f1_list": [
                0.6337285902503293,
                0.6240105540897096,
                0.6290216677609981
            ],
            "auc_list": [
                0.6901807389791759,
                0.6821388996637049,
                0.6856680043550397
            ]
        }
    },
    "word2vec_vs500_win5_sg0": {
        "catboost": {
            "f1": 0.7610631740911539,
            "auc": 0.8008515931220019,
            "f1_list": [
                0.7601115760111576,
                0.7611731843575419,
                0.761904761904762
            ],
            "auc_list": [
                0.8000113588714599,
                0.8009212769788302,
                0.8016221435157158
            ]
        },
        "lightgbm": {
            "f1": 0.7470217238962858,
            "auc": 0.7897684361129942,
            "f1_list": [
                0.747021723896286,
                0.747021723896286,
                0.747021723896286
            ],
            "auc_list": [
                0.7897684361129942,
                0.7897684361129942,
                0.7897684361129942
            ]
        },
        "knn": {
            "f1": 0.7044518458924364,
            "auc": 0.7572526595669692,
            "f1_list": [
                0.7170568561872911,
                0.6794478527607363,
                0.7168508287292817
            ],
            "auc_list": [
                0.7621881294959683,
                0.7450211287093059,
                0.7645487204956335
            ]
        },
        "randomforest": {
            "f1": 0.7250535302233595,
            "auc": 0.7753976511303889,
            "f1_list": [
                0.7248908296943232,
                0.7211184694628403,
                0.7291512915129151
            ],
            "auc_list": [
                0.7747173272333776,
                0.7725899556158139,
                0.7788856705419752
            ]
        },
        "decisiontree": {
            "f1": 0.6183967109792446,
            "auc": 0.6760030950910743,
            "f1_list": [
                0.6077275703994761,
                0.6217277486910995,
                0.6257348138471587
            ],
            "auc_list": [
                0.6670636229724716,
                0.6789173303751932,
                0.6820283319255582
            ]
        }
    },
    "word2vec_vs500_win8_sg0": {
        "catboost": {
            "f1": 0.766368583047948,
            "auc": 0.8051061349586993,
            "f1_list": [
                0.7618384401114205,
                0.7673928320449755,
                0.7698744769874477
            ],
            "auc_list": [
                0.8013393801197999,
                0.8061348781398519,
                0.8078441466164461
            ]
        },
        "lightgbm": {
            "f1": 0.7503526093088858,
            "auc": 0.7927440979183057,
            "f1_list": [
                0.7503526093088858,
                0.7503526093088858,
                0.7503526093088858
            ],
            "auc_list": [
                0.7927440979183056,
                0.7927440979183056,
                0.7927440979183056
            ]
        },
        "knn": {
            "f1": 0.707430360508301,
            "auc": 0.7571668638357297,
            "f1_list": [
                0.7179153094462541,
                0.6800296956198961,
                0.7243460764587526
            ],
            "auc_list": [
                0.7607743125163888,
                0.742242434568671,
                0.7684838444221295
            ]
        },
        "randomforest": {
            "f1": 0.7265060835923413,
            "auc": 0.7766928444346162,
            "f1_list": [
                0.7207074428887251,
                0.7311355311355311,
                0.7276752767527674
            ],
            "auc_list": [
                0.7723809040453291,
                0.7799309283943993,
                0.77776670086412
            ]
        },
        "decisiontree": {
            "f1": 0.6216426073926696,
            "auc": 0.6813272639902426,
            "f1_list": [
                0.6257585974376265,
                0.6216393442622951,
                0.6175298804780877
            ],
            "auc_list": [
                0.687081821334619,
                0.6791632378583935,
                0.6777367327777153
            ]
        }
    },
    "word2vec_vs500_win4_sg1": {
        "catboost": {
            "f1": 0.7702104264339683,
            "auc": 0.8085858970346497,
            "f1_list": [
                0.7696669029057407,
                0.7714083510261854,
                0.7695560253699789
            ],
            "auc_list": [
                0.8082374777505085,
                0.8095654989988484,
                0.8079547143545924
            ]
        },
        "lightgbm": {
            "f1": 0.7448177269478199,
            "auc": 0.7890796534819171,
            "f1_list": [
                0.7448177269478199,
                0.7448177269478199,
                0.7448177269478199
            ],
            "auc_list": [
                0.7890796534819171,
                0.7890796534819171,
                0.7890796534819171
            ]
        },
        "knn": {
            "f1": 0.7111663777082694,
            "auc": 0.765441721134872,
            "f1_list": [
                0.7315753887762002,
                0.687847498014297,
                0.7140762463343109
            ],
            "auc_list": [
                0.7750623227442067,
                0.754304589346587,
                0.7669582513138226
            ]
        },
        "randomforest": {
            "f1": 0.7073809619636814,
            "auc": 0.7660642436824333,
            "f1_list": [
                0.701945525291829,
                0.7094281298299846,
                0.7107692307692308
            ],
            "auc_list": [
                0.7626171081521653,
                0.7674742340918401,
                0.7681013888032945
            ]
        },
        "decisiontree": {
            "f1": 0.5979137816741162,
            "auc": 0.6650671603344986,
            "f1_list": [
                0.5941536369816451,
                0.5970149253731343,
                0.6025727826675694
            ],
            "auc_list": [
                0.6623291486767519,
                0.6643211805492619,
                0.668551151777482
            ]
        }
    },
    "word2vec_vs500_win3_sg1": {
        "catboost": {
            "f1": 0.7723614850255114,
            "auc": 0.8105245583231727,
            "f1_list": [
                0.7693409742120344,
                0.7735042735042735,
                0.7742392073602263
            ],
            "auc_list": [
                0.808348045488655,
                0.8114221911263046,
                0.8118034383545587
            ]
        },
        "lightgbm": {
            "f1": 0.7492753623188405,
            "auc": 0.7932479967905146,
            "f1_list": [
                0.7492753623188405,
                0.7492753623188405,
                0.7492753623188405
            ],
            "auc_list": [
                0.7932479967905146,
                0.7932479967905146,
                0.7932479967905146
            ]
        },
        "knn": {
            "f1": 0.7066865239534895,
            "auc": 0.7613593749559441,
            "f1_list": [
                0.7203791469194313,
                0.6861198738170348,
                0.7135605511240029
            ],
            "auc_list": [
                0.7659015137508806,
                0.7524478972191307,
                0.7657287138978208
            ]
        },
        "randomforest": {
            "f1": 0.705348681565054,
            "auc": 0.7644780296466545,
            "f1_list": [
                0.7064291247095275,
                0.6926070038910506,
                0.7170099160945843
            ],
            "auc_list": [
                0.76548220221933,
                0.7559032900850344,
                0.7720485966355989
            ]
        },
        "decisiontree": {
            "f1": 0.6192944242726428,
            "auc": 0.6792286923481888,
            "f1_list": [
                0.6151815181518152,
                0.6269052352551359,
                0.6157965194109772
            ],
            "auc_list": [
                0.6747610709724039,
                0.6853236130395011,
                0.6776013930326616
            ]
        }
    },
    "word2vec_vs500_win4_sg0": {
        "catboost": {
            "f1": 0.777708055730347,
            "auc": 0.8141030056298918,
            "f1_list": [
                0.7780097425191372,
                0.7741487143849896,
                0.780965710286914
            ],
            "auc_list": [
                0.8143120572003766,
                0.8111641997372959,
                0.8168327599520027
            ]
        },
        "lightgbm": {
            "f1": 0.7536842105263157,
            "auc": 0.7951542329317852,
            "f1_list": [
                0.7536842105263157,
                0.7536842105263157,
                0.7536842105263157
            ],
            "auc_list": [
                0.7951542329317852,
                0.7951542329317852,
                0.7951542329317852
            ]
        },
        "knn": {
            "f1": 0.7109778821735411,
            "auc": 0.761876163327682,
            "f1_list": [
                0.7270306258322237,
                0.6822641509433962,
                0.7236388697450035
            ],
            "auc_list": [
                0.7701931128987236,
                0.7455377156826137,
                0.7698976614017089
            ]
        },
        "randomforest": {
            "f1": 0.7279775883023544,
            "auc": 0.7781642613652154,
            "f1_list": [
                0.7265973254086181,
                0.7260579064587973,
                0.7312775330396476
            ],
            "auc_list": [
                0.7773854536358659,
                0.7769304945821808,
                0.7801768358775996
            ]
        },
        "decisiontree": {
            "f1": 0.6326515404181998,
            "auc": 0.6928283227417898,
            "f1_list": [
                0.638757596218771,
                0.6258411843876178,
                0.6333558406482107
            ],
            "auc_list": [
                0.6980624665426857,
                0.6868359138514187,
                0.6935865878312651
            ]
        }
    },
    "word2vec_vs500_win8_sg1": {
        "catboost": {
            "f1": 0.7780398404176451,
            "auc": 0.8150127223388318,
            "f1_list": [
                0.7777777777777778,
                0.7737330478229836,
                0.782608695652174
            ],
            "auc_list": [
                0.8147791001598701,
                0.8116680986095048,
                0.8185909682471207
            ]
        },
        "lightgbm": {
            "f1": 0.7587209302325583,
            "auc": 0.8006626813945311,
            "f1_list": [
                0.7587209302325583,
                0.7587209302325583,
                0.7587209302325583
            ],
            "auc_list": [
                0.8006626813945311,
                0.8006626813945311,
                0.8006626813945311
            ]
        },
        "knn": {
            "f1": 0.7024597278326663,
            "auc": 0.7596787050564298,
            "f1_list": [
                0.7166212534059946,
                0.6839126919967664,
                0.7068452380952381
            ],
            "auc_list": [
                0.7632823271669162,
                0.753123991749109,
                0.7626297962532641
            ]
        },
        "randomforest": {
            "f1": 0.711767755313634,
            "auc": 0.7696219469508478,
            "f1_list": [
                0.7122861586314153,
                0.7138413685847589,
                0.7091757387247279
            ],
            "auc_list": [
                0.7699949368434663,
                0.7711139065213214,
                0.7677569974877559
            ]
        },
        "decisiontree": {
            "f1": 0.626651123025075,
            "auc": 0.6848563686815773,
            "f1_list": [
                0.6360052562417872,
                0.6193633952254642,
                0.6245847176079734
            ],
            "auc_list": [
                0.6917178117980005,
                0.6790647540260553,
                0.6837865402206762
            ]
        }
    },
    "word2vec_vs500_win5_sg1": {
        "catboost": {
            "f1": 0.7713412284532586,
            "auc": 0.8095900696073254,
            "f1_list": [
                0.7710843373493976,
                0.7718550106609808,
                0.7710843373493976
            ],
            "auc_list": [
                0.8093564474283635,
                0.810057313965249,
                0.8093564474283635
            ]
        },
        "lightgbm": {
            "f1": 0.7474747474747475,
            "auc": 0.7916372121462588,
            "f1_list": [
                0.7474747474747475,
                0.7474747474747475,
                0.7474747474747475
            ],
            "auc_list": [
                0.7916372121462588,
                0.7916372121462588,
                0.7916372121462588
            ]
        },
        "knn": {
            "f1": 0.7128918284133734,
            "auc": 0.7665729761169658,
            "f1_list": [
                0.7273963290278722,
                0.6951026856240128,
                0.7161764705882352
            ],
            "auc_list": [
                0.7719881771065571,
                0.758952663715777,
                0.7687780875285632
            ]
        },
        "randomforest": {
            "f1": 0.7045844079097309,
            "auc": 0.7646459959373907,
            "f1_list": [
                0.7012578616352201,
                0.7065217391304348,
                0.7059736229635377
            ],
            "auc_list": [
                0.7629367274607968,
                0.7657281097025305,
                0.7652731506488453
            ]
        },
        "decisiontree": {
            "f1": 0.6023895261783669,
            "auc": 0.6691946197617779,
            "f1_list": [
                0.5863013698630138,
                0.6165311653116532,
                0.6043360433604337
            ],
            "auc_list": [
                0.6572629711665923,
                0.6801958076097188,
                0.6701250805090224
            ]
        }
    },
    "word2vec_vs1000_win5_sg1": {
        "catboost": {
            "f1": 0.7751380532500866,
            "auc": 0.8124551636744902,
            "f1_list": [
                0.7767540751240255,
                0.7785613540197461,
                0.7700987306064879
            ],
            "auc_list": [
                0.8138323261397842,
                0.8151234914754086,
                0.8084096734082777
            ]
        },
        "lightgbm": {
            "f1": 0.7616320687186832,
            "auc": 0.8022982380456941,
            "f1_list": [
                0.761632068718683,
                0.761632068718683,
                0.761632068718683
            ],
            "auc_list": [
                0.8022982380456941,
                0.8022982380456941,
                0.8022982380456941
            ]
        },
        "knn": {
            "f1": 0.7151710249119053,
            "auc": 0.7690445376516379,
            "f1_list": [
                0.7379679144385026,
                0.6844229217110575,
                0.723122238586156
            ],
            "auc_list": [
                0.7796366852879656,
                0.7533330433195938,
                0.7741638843473543
            ]
        },
        "randomforest": {
            "f1": 0.7086887591003165,
            "auc": 0.7672077839687654,
            "f1_list": [
                0.702660406885759,
                0.7161639597834494,
                0.7072419106317412
            ],
            "auc_list": [
                0.7635638821722512,
                0.7724050718569458,
                0.7656543978770993
            ]
        },
        "decisiontree": {
            "f1": 0.6038573899369112,
            "auc": 0.6668871979476695,
            "f1_list": [
                0.6191744340878829,
                0.5962566844919787,
                0.5961410512308717
            ],
            "auc_list": [
                0.679556568992456,
                0.6610258994353191,
                0.6600791254152332
            ]
        }
    },
    "word2vec_vs1000_win4_sg0": {
        "catboost": {
            "f1": 0.7733069190431777,
            "auc": 0.8106067288826697,
            "f1_list": [
                0.7704117236566644,
                0.775766016713092,
                0.7737430167597765
            ],
            "auc_list": [
                0.8082991056701312,
                0.8125290768983514,
                0.8109920040795267
            ]
        },
        "lightgbm": {
            "f1": 0.7562189054726368,
            "auc": 0.7977486475088426,
            "f1_list": [
                0.7562189054726368,
                0.7562189054726368,
                0.7562189054726368
            ],
            "auc_list": [
                0.7977486475088426,
                0.7977486475088426,
                0.7977486475088426
            ]
        },
        "knn": {
            "f1": 0.700911903340916,
            "auc": 0.753740069546906,
            "f1_list": [
                0.7067371202113606,
                0.6774193548387096,
                0.7185792349726777
            ],
            "auc_list": [
                0.7524249377980948,
                0.743693107460966,
                0.7651021633816569
            ]
        },
        "randomforest": {
            "f1": 0.7307860607316418,
            "auc": 0.7798038459849813,
            "f1_list": [
                0.7338235294117648,
                0.7309941520467836,
                0.7275405007363769
            ],
            "auc_list": [
                0.7822057236628251,
                0.779685020911199,
                0.7775207933809196
            ]
        },
        "decisiontree": {
            "f1": 0.6078875998030023,
            "auc": 0.6693670168179774,
            "f1_list": [
                0.6023936170212767,
                0.6154873164218958,
                0.6057818659658344
            ],
            "auc_list": [
                0.6652190147508238,
                0.676900526495776,
                0.6659815092073321
            ]
        }
    },
    "word2vec_vs1000_win8_sg1": {
        "catboost": {
            "f1": 0.7852752019986946,
            "auc": 0.8203904632204173,
            "f1_list": [
                0.7837648705388384,
                0.7796610169491526,
                0.7923997185080928
            ],
            "auc_list": [
                0.819070699307713,
                0.816033409582779,
                0.8260672807707599
            ]
        },
        "lightgbm": {
            "f1": 0.7462039045553143,
            "auc": 0.7907641499516039,
            "f1_list": [
                0.7462039045553144,
                0.7462039045553144,
                0.7462039045553144
            ],
            "auc_list": [
                0.7907641499516039,
                0.7907641499516039,
                0.7907641499516039
            ]
        },
        "knn": {
            "f1": 0.7047521759141636,
            "auc": 0.7603018317992815,
            "f1_list": [
                0.7119784656796769,
                0.6831604150039905,
                0.7191176470588234
            ],
            "auc_list": [
                0.7584499732341486,
                0.7514394952794221,
                0.7710160268842735
            ]
        },
        "randomforest": {
            "f1": 0.709550601290372,
            "auc": 0.7681422726846128,
            "f1_list": [
                0.7145085803432137,
                0.7140649149922721,
                0.7000783085356304
            ],
            "auc_list": [
                0.7718147730582069,
                0.7708311431254055,
                0.7617809018702261
            ]
        },
        "decisiontree": {
            "f1": 0.6206400436650902,
            "auc": 0.6839502771443797,
            "f1_list": [
                0.6206425153793576,
                0.6247464503042596,
                0.6165311653116532
            ],
            "auc_list": [
                0.6849913056297708,
                0.6866637181936492,
                0.6801958076097188
            ]
        }
    },
    "word2vec_vs1000_win3_sg1": {
        "catboost": {
            "f1": 0.7771218500159273,
            "auc": 0.8138979820280096,
            "f1_list": [
                0.7704225352112677,
                0.7780898876404494,
                0.7828531271960647
            ],
            "auc_list": [
                0.8086187249787624,
                0.814631676509008,
                0.8184435445962586
            ]
        },
        "lightgbm": {
            "f1": 0.7623833452979182,
            "auc": 0.8029991045825796,
            "f1_list": [
                0.7623833452979182,
                0.7623833452979182,
                0.7623833452979182
            ],
            "auc_list": [
                0.8029991045825796,
                0.8029991045825796,
                0.8029991045825796
            ]
        },
        "knn": {
            "f1": 0.6985687442542572,
            "auc": 0.7559407501930404,
            "f1_list": [
                0.7248500999333777,
                0.6720257234726688,
                0.6988304093567251
            ],
            "auc_list": [
                0.7684101325966984,
                0.7443444299840373,
                0.7550676879983855
            ]
        },
        "randomforest": {
            "f1": 0.7151346717607964,
            "auc": 0.7711427064968314,
            "f1_list": [
                0.7126436781609196,
                0.7146136189747514,
                0.7181467181467182
            ],
            "auc_list": [
                0.7691835025684342,
                0.7705115238167742,
                0.7737330931052858
            ]
        },
        "decisiontree": {
            "f1": 0.6214975909192276,
            "auc": 0.6826961691199008,
            "f1_list": [
                0.6216216216216216,
                0.6262491672218521,
                0.6166219839142092
            ],
            "auc_list": [
                0.6839708197842539,
                0.6856063764354169,
                0.6785113111400319
            ]
        }
    },
    "word2vec_vs1000_win8_sg0": {
        "catboost": {
            "f1": 0.7699772903525082,
            "auc": 0.8079138304732743,
            "f1_list": [
                0.7693379790940768,
                0.7716863289382374,
                0.7689075630252102
            ],
            "auc_list": [
                0.8073891875627608,
                0.8091353119520703,
                0.8072169919049915
            ]
        },
        "lightgbm": {
            "f1": 0.7459535538353274,
            "auc": 0.7891412814015396,
            "f1_list": [
                0.7459535538353272,
                0.7459535538353272,
                0.7459535538353272
            ],
            "auc_list": [
                0.7891412814015396,
                0.7891412814015396,
                0.7891412814015396
            ]
        },
        "knn": {
            "f1": 0.7005370037553936,
            "auc": 0.7522400540392268,
            "f1_list": [
                0.7153094462540718,
                0.6757575757575758,
                0.7105439892545333
            ],
            "auc_list": [
                0.7585363731606786,
                0.7410986928839087,
                0.7570850960730932
            ]
        },
        "randomforest": {
            "f1": 0.7213354505676063,
            "auc": 0.7726473541684036,
            "f1_list": [
                0.716285924834193,
                0.7191176470588234,
                0.7286027798098024
            ],
            "auc_list": [
                0.7690239950117636,
                0.7710160268842735,
                0.7779020406091738
            ]
        },
        "decisiontree": {
            "f1": 0.6243946141465856,
            "auc": 0.6809913314087698,
            "f1_list": [
                0.6267880364109232,
                0.617300131061599,
                0.6290956749672346
            ],
            "auc_list": [
                0.6822005275833275,
                0.6753513697711429,
                0.6854220968718392
            ]
        }
    },
    "word2vec_vs1000_win4_sg1": {
        "catboost": {
            "f1": 0.7814720135811365,
            "auc": 0.8173122896141649,
            "f1_list": [
                0.7792571829011913,
                0.7820602662929222,
                0.7830985915492957
            ],
            "auc_list": [
                0.8155047387036627,
                0.8177426780593731,
                0.8186894520794589
            ]
        },
        "lightgbm": {
            "f1": 0.7671809256661991,
            "auc": 0.8058889706566515,
            "f1_list": [
                0.7671809256661991,
                0.7671809256661991,
                0.7671809256661991
            ],
            "auc_list": [
                0.8058889706566515,
                0.8058889706566515,
                0.8058889706566515
            ]
        },
        "knn": {
            "f1": 0.7082707723453248,
            "auc": 0.763531658423429,
            "f1_list": [
                0.730329522528581,
                0.6869495596477182,
                0.707533234859675
            ],
            "auc_list": [
                0.7736605896704357,
                0.754378301172018,
                0.7625560844278331
            ]
        },
        "randomforest": {
            "f1": 0.718859860780634,
            "auc": 0.7739052887630552,
            "f1_list": [
                0.7292143401983219,
                0.7141750580945004,
                0.7131901840490797
            ],
            "auc_list": [
                0.7810003540584403,
                0.7710770506086059,
                0.7696384616221194
            ]
        },
        "decisiontree": {
            "f1": 0.6185177953247358,
            "auc": 0.679195864404076,
            "f1_list": [
                0.6204620462046204,
                0.6189839572192514,
                0.6161073825503356
            ],
            "auc_list": [
                0.6792369496838245,
                0.6800483839588567,
                0.6783022595695469
            ]
        }
    },
    "word2vec_vs1000_win5_sg0": {
        "catboost": {
            "f1": 0.7709874353570664,
            "auc": 0.8088483191891216,
            "f1_list": [
                0.7689075630252102,
                0.7711686494051785,
                0.7728860936408106
            ],
            "auc_list": [
                0.8072169919049915,
                0.8089999722070167,
                0.8103279934553567
            ]
        },
        "lightgbm": {
            "f1": 0.7593507410021171,
            "auc": 0.7999128750391217,
            "f1_list": [
                0.7593507410021171,
                0.7593507410021171,
                0.7593507410021171
            ],
            "auc_list": [
                0.7999128750391217,
                0.7999128750391217,
                0.7999128750391217
            ]
        },
        "knn": {
            "f1": 0.7019657192121561,
            "auc": 0.7541581726878754,
            "f1_list": [
                0.7055702917771884,
                0.6802721088435374,
                0.7200547570157427
            ],
            "auc_list": [
                0.7517977830866404,
                0.7442096944342738,
                0.7664670405427124
            ]
        },
        "randomforest": {
            "f1": 0.729699199533642,
            "auc": 0.7788939278776109,
            "f1_list": [
                0.7274063188831742,
                0.7282127031019202,
                0.7334785766158316
            ],
            "auc_list": [
                0.7772748858977193,
                0.7782216599178053,
                0.7811852378173082
            ]
        },
        "decisiontree": {
            "f1": 0.6197080688947695,
            "auc": 0.6781630932543207,
            "f1_list": [
                0.6246719160104988,
                0.6105263157894737,
                0.6239259748843358
            ],
            "auc_list": [
                0.6818561362677891,
                0.6702483363482677,
                0.6823848071469052
            ]
        }
    },
    "word2vec_vs1000_win3_sg0": {
        "catboost": {
            "f1": 0.7675667923744403,
            "auc": 0.8056595778447226,
            "f1_list": [
                0.7624309392265194,
                0.7700831024930748,
                0.7701863354037267
            ],
            "auc_list": [
                0.8014747198648536,
                0.8077704347910148,
                0.8077335788782993
            ]
        },
        "lightgbm": {
            "f1": 0.7434996486296557,
            "auc": 0.7871123936163142,
            "f1_list": [
                0.7434996486296557,
                0.7434996486296557,
                0.7434996486296557
            ],
            "auc_list": [
                0.7871123936163142,
                0.7871123936163142,
                0.7871123936163142
            ]
        },
        "knn": {
            "f1": 0.7015447861737486,
            "auc": 0.7547810980322972,
            "f1_list": [
                0.7095046854082998,
                0.6778882938026013,
                0.7172413793103448
            ],
            "auc_list": [
                0.7559292704825225,
                0.7436562515482504,
                0.7647577720661184
            ]
        },
        "randomforest": {
            "f1": 0.728423637107777,
            "auc": 0.778279058470395,
            "f1_list": [
                0.72953216374269,
                0.7306273062730628,
                0.725111441307578
            ],
            "auc_list": [
                0.7785660512333438,
                0.7800046402198304,
                0.7762664839580108
            ]
        },
        "decisiontree": {
            "f1": 0.630240968970614,
            "auc": 0.6876763495003909,
            "f1_list": [
                0.6455862977602108,
                0.6191419141914192,
                0.6259946949602122
            ],
            "auc_list": [
                0.7002514660798721,
                0.6781179800059695,
                0.6846596024153311
            ]
        }
    },
    "word2vec_vs1000_win7_sg1": {
        "catboost": {
            "f1": 0.7821955621186789,
            "auc": 0.8180500120637659,
            "f1_list": [
                0.7762039660056658,
                0.7886925795053004,
                0.7816901408450704
            ],
            "auc_list": [
                0.8133773670860991,
                0.823202186703595,
                0.8175704824016038
            ]
        },
        "lightgbm": {
            "f1": 0.7665952890792291,
            "auc": 0.8060732502202294,
            "f1_list": [
                0.7665952890792291,
                0.7665952890792291,
                0.7665952890792291
            ],
            "auc_list": [
                0.8060732502202292,
                0.8060732502202292,
                0.8060732502202292
            ]
        },
        "knn": {
            "f1": 0.7060585436901232,
            "auc": 0.7618429325867092,
            "f1_list": [
                0.7180174146014736,
                0.6860841423948221,
                0.7140740740740741
            ],
            "auc_list": [
                0.7630980476033385,
                0.7546979204806494,
                0.7677328296761392
            ]
        },
        "randomforest": {
            "f1": 0.7183870351770394,
            "auc": 0.7742249080716865,
            "f1_list": [
                0.7189440993788819,
                0.7199379363847943,
                0.7162790697674418
            ],
            "auc_list": [
                0.7746798671253717,
                0.7753438777495416,
                0.7726509793401463
            ]
        },
        "decisiontree": {
            "f1": 0.5984798523870385,
            "auc": 0.6617801365561916,
            "f1_list": [
                0.5993311036789297,
                0.6049300466355763,
                0.5911784068466096
            ],
            "auc_list": [
                0.6637187978447145,
                0.6677028615897345,
                0.6539187502341257
            ]
        }
    },
    "word2vec_vs1000_win6_sg0": {
        "catboost": {
            "f1": 0.7699956791678503,
            "auc": 0.8079015451690358,
            "f1_list": [
                0.7679442508710802,
                0.7794729542302359,
                0.7625698324022346
            ],
            "auc_list": [
                0.8062702178849057,
                0.8153941709655161,
                0.8020402466566854
            ]
        },
        "lightgbm": {
            "f1": 0.7559943582510579,
            "auc": 0.7972199766297262,
            "f1_list": [
                0.7559943582510578,
                0.7559943582510578,
                0.7559943582510578
            ],
            "auc_list": [
                0.7972199766297262,
                0.7972199766297262,
                0.7972199766297262
            ]
        },
        "knn": {
            "f1": 0.7090026376002511,
            "auc": 0.7606997950972372,
            "f1_list": [
                0.723658051689861,
                0.6774441878367975,
                0.7259056732740945
            ],
            "auc_list": [
                0.7670083995229274,
                0.7439390149441663,
                0.7711519708246178
            ]
        },
        "randomforest": {
            "f1": 0.7329543524856642,
            "auc": 0.7813532041080445,
            "f1_list": [
                0.7259368111682587,
                0.7343065693430656,
                0.7386196769456682
            ],
            "auc_list": [
                0.7761559162198642,
                0.7821320118373941,
                0.7857716842668754
            ]
        },
        "decisiontree": {
            "f1": 0.6174561305273348,
            "auc": 0.6763801129522955,
            "f1_list": [
                0.6088682991396427,
                0.618828176431863,
                0.6246719160104988
            ],
            "auc_list": [
                0.6698670891200137,
                0.6774171134690838,
                0.6818561362677891
            ]
        }
    },
    "word2vec_vs1000_win6_sg1": {
        "catboost": {
            "f1": 0.781897310800369,
            "auc": 0.8178409604932813,
            "f1_list": [
                0.7787234042553192,
                0.7860696517412936,
                0.7808988764044944
            ],
            "auc_list": [
                0.8154062548713246,
                0.8212470107438007,
                0.8168696158647183
            ]
        },
        "lightgbm": {
            "f1": 0.7638989169675091,
            "auc": 0.8044008376563507,
            "f1_list": [
                0.7638989169675091,
                0.7638989169675091,
                0.7638989169675091
            ],
            "auc_list": [
                0.8044008376563507,
                0.8044008376563507,
                0.8044008376563507
            ]
        },
        "knn": {
            "f1": 0.7027120920745279,
            "auc": 0.7597689315531323,
            "f1_list": [
                0.7217741935483871,
                0.6736672051696284,
                0.7126948775055679
            ],
            "auc_list": [
                0.7664918125496196,
                0.7459552146282931,
                0.7668597674814844
            ]
        },
        "randomforest": {
            "f1": 0.7048108107766903,
            "auc": 0.764539456167847,
            "f1_list": [
                0.7080745341614907,
                0.7075252133436774,
                0.6988326848249028
            ],
            "auc_list": [
                0.7668470793803855,
                0.7663921203267005,
                0.760379168796455
            ]
        },
        "decisiontree": {
            "f1": 0.6180672567776767,
            "auc": 0.6802614634979443,
            "f1_list": [
                0.6241699867197875,
                0.6137135098438561,
                0.6163182737693864
            ],
            "auc_list": [
                0.6833315811669911,
                0.6782037757372088,
                0.679249033589633
            ]
        }
    },
    "word2vec_vs1000_win7_sg0": {
        "catboost": {
            "f1": 0.7744853665619932,
            "auc": 0.8115863308468684,
            "f1_list": [
                0.7726638772663877,
                0.7799442896935933,
                0.7708479327259986
            ],
            "auc_list": [
                0.8100820859721563,
                0.8158859859319169,
                0.8087909206365319
            ]
        },
        "lightgbm": {
            "f1": 0.7594038325053228,
            "auc": 0.8001956384350374,
            "f1_list": [
                0.7594038325053228,
                0.7594038325053228,
                0.7594038325053228
            ],
            "auc_list": [
                0.8001956384350375,
                0.8001956384350375,
                0.8001956384350375
            ]
        },
        "knn": {
            "f1": 0.6996920519714821,
            "auc": 0.7521743981510013,
            "f1_list": [
                0.7129750982961993,
                0.6762917933130699,
                0.7098092643051771
            ],
            "auc_list": [
                0.7570361562545692,
                0.7417995594207942,
                0.7576874787776404
            ]
        },
        "randomforest": {
            "f1": 0.7275450288114781,
            "auc": 0.7773445697545475,
            "f1_list": [
                0.7276720351390921,
                0.7200587803085966,
                0.7349042709867453
            ],
            "auc_list": [
                0.7772380299850038,
                0.7716800375084435,
                0.7831156417701954
            ]
        },
        "decisiontree": {
            "f1": 0.6232432557424048,
            "auc": 0.6827495397038877,
            "f1_list": [
                0.6253333333333333,
                0.614569536423841,
                0.6298268974700401
            ],
            "auc_list": [
                0.6849423658112469,
                0.6747979268851195,
                0.6885083264152971
            ]
        }
    }
}